{
    "input_path": "C:\\Users\\vzhu0\\PycharmProjects\\yearbook-sports-git\\output\\turkeytail197000glen\\pages_gray\\page0012.jpg",
    "page_index": null,
    "model_settings": {
        "use_doc_preprocessor": true,
        "use_seal_recognition": false,
        "use_table_recognition": false,
        "use_formula_recognition": false,
        "use_chart_recognition": false,
        "use_region_detection": true
    },
    "parsing_res_list": [
        {
            "block_label": "text",
            "block_content": "a time to weep,",
            "block_bbox": [
                1679,
                829,
                2197,
                906
            ]
        },
        {
            "block_label": "image",
            "block_content": "",
            "block_bbox": [
                0,
                1895,
                772,
                2668
            ]
        },
        {
            "block_label": "image",
            "block_content": "",
            "block_bbox": [
                0,
                220,
                1014,
                1582
            ]
        },
        {
            "block_label": "figure_title",
            "block_content": "and a time to laugh;",
            "block_bbox": [
                474,
                1753,
                1153,
                1836
            ]
        },
        {
            "block_label": "image",
            "block_content": "",
            "block_bbox": [
                829,
                1890,
                1615,
                2674
            ]
        },
        {
            "block_label": "image",
            "block_content": "",
            "block_bbox": [
                499,
                2745,
                1319,
                3476
            ]
        },
        {
            "block_label": "image",
            "block_content": "",
            "block_bbox": [
                1684,
                1731,
                2574,
                2595
            ]
        }
    ],
    "doc_preprocessor_res": {
        "input_path": null,
        "page_index": null,
        "model_settings": {
            "use_doc_orientation_classify": false,
            "use_doc_unwarping": false
        },
        "angle": -1
    },
    "layout_det_res": {
        "input_path": null,
        "page_index": null,
        "boxes": [
            {
                "cls_id": 1,
                "label": "image",
                "score": 0.7484431862831116,
                "coordinate": [
                    0.709716796875,
                    220.6265869140625,
                    1014.5489501953125,
                    1582.9720458984375
                ]
            },
            {
                "cls_id": 1,
                "label": "image",
                "score": 0.6784722805023193,
                "coordinate": [
                    829.3076782226562,
                    1890.67431640625,
                    1615.03759765625,
                    2674.1201171875
                ]
            },
            {
                "cls_id": 1,
                "label": "image",
                "score": 0.6561400890350342,
                "coordinate": [
                    1684.9989013671875,
                    1731.5819091796875,
                    2574,
                    2595.73828125
                ]
            },
            {
                "cls_id": 6,
                "label": "figure_title",
                "score": 0.6503427028656006,
                "coordinate": [
                    474.4912414550781,
                    1753.279541015625,
                    1153.324462890625,
                    1836.833251953125
                ]
            },
            {
                "cls_id": 1,
                "label": "image",
                "score": 0.6437686085700989,
                "coordinate": [
                    499.47784423828125,
                    2745.87841796875,
                    1319.6318359375,
                    3476
                ]
            },
            {
                "cls_id": 1,
                "label": "image",
                "score": 0.5759879350662231,
                "coordinate": [
                    0,
                    1895.95751953125,
                    772.44384765625,
                    2668.40234375
                ]
            },
            {
                "cls_id": 2,
                "label": "text",
                "score": 0.4353519082069397,
                "coordinate": [
                    1679.549072265625,
                    829.9739990234375,
                    2197.000732421875,
                    906.1036376953125
                ]
            }
        ]
    },
    "overall_ocr_res": {
        "input_path": null,
        "page_index": null,
        "model_settings": {
            "use_doc_preprocessor": false,
            "use_textline_orientation": true
        },
        "dt_polys": [
            [
                [
                    1682,
                    830
                ],
                [
                    2202,
                    830
                ],
                [
                    2202,
                    920
                ],
                [
                    1682,
                    920
                ]
            ],
            [
                [
                    472,
                    1756
                ],
                [
                    1153,
                    1748
                ],
                [
                    1154,
                    1838
                ],
                [
                    473,
                    1845
                ]
            ]
        ],
        "text_det_params": {
            "limit_side_len": 2000,
            "limit_type": "max",
            "thresh": 0.3,
            "max_side_limit": 4000,
            "box_thresh": 0.6,
            "unclip_ratio": 1.5
        },
        "text_type": "general",
        "textline_orientation_angles": [
            0,
            0
        ],
        "text_rec_score_thresh": 0.7,
        "return_word_box": false,
        "rec_texts": [
            "a time to weep,",
            "and a time to laugh;"
        ],
        "rec_scores": [
            0.9541721343994141,
            0.9618674516677856
        ],
        "rec_polys": [
            [
                [
                    1682,
                    830
                ],
                [
                    2202,
                    830
                ],
                [
                    2202,
                    920
                ],
                [
                    1682,
                    920
                ]
            ],
            [
                [
                    472,
                    1756
                ],
                [
                    1153,
                    1748
                ],
                [
                    1154,
                    1838
                ],
                [
                    473,
                    1845
                ]
            ]
        ],
        "rec_boxes": [
            [
                1682,
                830,
                2202,
                920
            ],
            [
                472,
                1748,
                1154,
                1845
            ]
        ]
    }
}